{
  "name": "microsoft-office-365-feed",
  "label": "Microsoft Office 365 Feed",
  "version": "1.0.0",
  "description": "Ingest the IP, URLs used by Office 365 using the web service provided by Microsoft. The fetched indicators can be used to create a whitelist, blacklist etc. for your SIEM or firewall services.\\nThis connector has a dependency on the <a href=\"/content-hub/all-content/?contentType=solutionpack&amp;tag=ThreatIntelManagement\" target=\"_blank\" rel=\"noopener\">Threat Intel Management Solution Pack</a>. Install the Solution Pack before enabling ingestion of Threat Feeds from this source.",
  "publisher": "Fortinet",
  "cs_approved": true,
  "cs_compatible": true,
  "category": "Threat Intelligence",
  "icon_small_name": "office365_feed_32x32.png",
  "icon_large_name": "office365_feed_80x80.png",
  "ingestion_supported": true,
  "ingestion_modes": [
    "scheduled"
  ],
  "ingestion_preferences": {
    "modules": ["threat_intel_feeds", "indicators"]
  },
  "tags": [
    "ThreatIntel"
  ],
  "help_online": "https://docs.fortinet.com/document/fortisoar/1.0.0/microsoft-office-365-feed/245/microsoft-office-365-feed-v1-0-0",
  "configuration": {
    "fields": [
      {
        "title": "Regions",
        "required": true,
        "editable": true,
        "visible": true,
        "type": "select",
        "value": "Worldwide",
        "options": ["China", "Germany", "USGovDoD","USGovGCCHigh","Worldwide"],
        "description": "Select the regions from where you want to fetch indicators. You can select multiple regions. If you want to retrieve indicators from all regions, then you need to individually select each region.",
        "name": "regions"
      },
      {
        "title": "Services",
        "required": true,
        "editable": true,
        "visible": true,
        "type": "multiselect",
        "value": "All",
        "options": ["Common", "Exchange", "Sharepoint","Skype", "All"],
        "description": "Select the services for which you want to fetch indicators. If you want to retrieve indicators for all services, select the “All” option.",
        "name": "services"
      },
      {
        "title": "Verify SSL",
        "required": false,
        "editable": true,
        "visible": true,
        "type": "checkbox",
        "name": "verify_ssl",
        "description": "Specifies whether the SSL certificate for the server is to be verified or not. By default, this option is set as True. ",
        "value": true
      }
    ]
  },
  "operations": [
    {
      "operation": "fetch_indicator",
      "title": "Fetch Indicators",
      "description": "Fetch indicators for an IP Address or a URL or both from the Microsoft Office 365 Feeds.",
      "category": "investigation",
      "annotation": "fetch_indicators",
      "enabled": true,
      "parameters": [
        {
          "title": "Indicator Type",
          "name": "indicator_type",
          "required": true,
          "visible": true,
          "editable": true,
          "type": "select",
          "options": [
            "IPs",
            "URLs",
            "Both"
          ],
          "description": "Select the type of indicator that you want to fetch from Office 365 Feeds. You can choose from the following options: IPs, URLs, or Both."
        },
        {
          "title": "Modified After",
          "name": "last_pull_time",
          "visible": true,
          "required": false,
          "editable": true,
          "type": "datetime",
          "tooltip": "Value as an Epoch Timestamp. Indicators data will be returned only if the feed has been refreshed after this time.",
          "description": "(Optional) Specify the value as an Epoch Timestamp. Specify the time the feeds were last pulled from Microsoft Office 365 Feeds. In this case, the indicators will be returned from Microsoft Office 365 Feeds only if the feed has been refreshed after the specified time. This is used in scheduled data ingestion to fetch feeds incrementally since the last successful pull."
        },
        {
          "title": "Limit",
          "required": false,
          "editable": true,
          "visible": true,
          "type": "integer",
          "name": "limit",
          "description": "(Optional) Specify the maximum number of indicators that should be returned in a single required. This controls the number of indicators by limiting feeds count in a single request. Note: The option of Pagination is not available.",
          "value": 10
        }
      ],
      "output_schema": {
        "lastUpdated": "",
        "region": "",
        "feedURL": "",
        "indicators": [
            {
                "value": "",
                "type": "",
                "id": "",
                "serviceArea": "",
                "serviceAreaDisplayName": "",
                "tcpPorts": "",
                "udpPorts": "",
                "expressRoute": "",
                "category": "",
                "required": ""
            }
        ]
    }
    }
  ]
}
